servicex_for_trexfitter/__init__.py
servicex_for_trexfitter/communicate_servicex.py
servicex_for_trexfitter/load_servicex_requests.py
servicex_for_trexfitter/make_ntuples.py
servicex_for_trexfitter/read_trex_config.py
servicex_for_trexfitter/servicex_for_trexfitter.py
servicex_for_trexfitter-1.1.0.dist-info/LICENSE
servicex_for_trexfitter-1.1.0.dist-info/METADATA
servicex_for_trexfitter-1.1.0.dist-info/WHEEL
servicex_for_trexfitter-1.1.0.dist-info/top_level.txt
servicex_for_trexfitter-1.1.0.dist-info/RECORD
