Metadata-Version: 2.1
Name: servicex-for-trexfitter
Version: 1.1.0
Summary: Interface ServiceX into TRExFitter to provide an alternative method of reading input ntuples
Home-page: https://github.com/kyungeonchoi/ServiceXforTRExFitter
Author: KyungEon Choi (UT Austin)
Author-email: kyungeonchoi@utexas.edu
License: BSD 3-clause
Platform: Any
Classifier: Development Status :: 3 - Alpha
Classifier: Intended Audience :: Developers
Classifier: Intended Audience :: Information Technology
Classifier: Intended Audience :: Science/Research
Classifier: Programming Language :: Python
Classifier: Topic :: Scientific/Engineering :: Physics
Classifier: Topic :: Software Development
Classifier: Topic :: Utilities
Requires-Python: >=3.6
License-File: LICENSE
Requires-Dist: tcut-to-qastle (>=0.6)
Requires-Dist: servicex (<2.5,>=2.4)
Requires-Dist: nest-asyncio (>=1.5.1)
Requires-Dist: numpy (<1.20.0,>=1.15.4)
Requires-Dist: uproot (>=4.1.5)
Requires-Dist: tqdm (>=4.60.0)
Requires-Dist: pyarrow (<6.0.0,>=5.0.0)
